db_timetable_api/__init__.py
db_timetable_api/timetable.py
db_timetable_api-1.0.0.dist-info/LICENSE.txt
db_timetable_api-1.0.0.dist-info/METADATA
db_timetable_api-1.0.0.dist-info/WHEEL
db_timetable_api-1.0.0.dist-info/top_level.txt
db_timetable_api-1.0.0.dist-info/RECORD
