Metadata-Version: 2.1
Name: db-timetable-api
Version: 1.0.0
Summary: Simple access to the Deutsche Bahn timetable API
Author: Sebastian Speetzen
Author-email: <sebastianspeetzen@googlemail.com>
Keywords: python,api,trains,db,deutsche bahn,fahrplan,timetable api,timetable,train timetable,train timetable api,train timetable api,train timetable,train,trains,train station,train stations,train station api,train station timetable,train station timetable api,train station timetable api,train station timetable,train station,train stations,train station api,train station timetable,train station timetable api,train station timetable api,train station timetable,train station,train stations,train 
Classifier: Development Status :: 5 - Production/Stable
Classifier: Intended Audience :: Developers
Classifier: License :: OSI Approved :: MIT License
Classifier: Programming Language :: Python :: 3
Classifier: Operating System :: Unix
Classifier: Operating System :: MacOS :: MacOS X
Classifier: Operating System :: Microsoft :: Windows
License-File: LICENSE.txt
Requires-Dist: requests
